hello_server/__init__.py
hello_server/server.py
hello_server-0.1.0.dist-info/WHEEL
hello_server-0.1.0.dist-info/entry_points.txt
hello_server-0.1.0.dist-info/METADATA
hello_server-0.1.0.dist-info/RECORD
