Metadata-Version: 2.3
Name: hello-server
Version: 0.1.0
Summary: An MCP server built with Smithery
Author: Your Name
Author-email: Your Name <your.email@example.com>
Requires-Dist: mcp>=1.14.0
Requires-Dist: smithery>=0.1.25
Requires-Python: >=3.10
